beemodoro/__init__.py
beemodoro/track_goal.py
beemodoro-1.2.0.dist-info/DESCRIPTION.rst
beemodoro-1.2.0.dist-info/entry_points.txt
beemodoro-1.2.0.dist-info/METADATA
beemodoro-1.2.0.dist-info/metadata.json
beemodoro-1.2.0.dist-info/RECORD
beemodoro-1.2.0.dist-info/top_level.txt
beemodoro-1.2.0.dist-info/WHEEL
