Metadata-Version: 2.0
Name: beemodoro
Version: 1.2.0
Summary: Beeminder Pomodoro Timer
Home-page: https://github.com/justuswilhelm/beemodoro
Author: Justus Perlwitz
Author-email: hello@justus.pw
License: MIT
Platform: UNKNOWN
Classifier: License :: OSI Approved :: MIT License
Classifier: Programming Language :: Python :: 3.3
Classifier: Programming Language :: Python :: 3.4
Requires-Dist: requests (==2.7.0)
